{
    "name": "wb_business",
    "orig": "source",
    "dest": "other",
    "source": [
        "hb_work"
    ],
    "area": "all",
    "struct": "mode>dest",
    "impedance_transform": {},
    "impedance_share": {
        "car_work": {
            "aht": [
                0.3693,
                0.0276
              ],
              "pt": [
                0.5897,
                0.6967
              ],
              "iht": [
                0.041,
                0.2757
              ]
            },
        "car_pax": {
            "aht": [
                0.3693,
                0.0276
              ],
              "pt": [
                0.5897,
                0.6967
              ],
              "iht": [
                0.041,
                0.2757
              ]
            },
        "transit_work": {
            "aht": [
                0.3693,
                0.0276
              ],
              "pt": [
                0.5897,
                0.6967
              ],
              "iht": [
                0.041,
                0.2757
              ]
            },
        "bike": {
            "aht": [
                0.3693,
                0.0276
              ],
              "pt": [
                0.5897,
                0.6967
              ],
              "iht": [
                0.041,
                0.2757
              ]
            },
        "walk": {
            "aht": [
                0.3693,
                0.0276
              ],
              "pt": [
                0.5897,
                0.6967
              ],
              "iht": [
                0.041,
                0.2757
              ]
            }
    },
    "distance_boundaries": {
        "car_work": [
            0,
            100
        ],
        "car_pax": [
            0,
            100
        ],
        "transit_work": [
            0,
            100
        ],
        "bike": [
            0,
            100
        ],
        "walk": [
            0,
            100
        ]
    },
    "destination_choice": {
      "car_work": {
          "attraction": {
              "within_zone_time": -0.0349
          },
          "impedance": {
              "time": -0.0349
          },
          "log": {
              "attraction_size": 1
          },
          "attraction_size": {
              "workplaces": 1
          }
      },
      "car_pax": {
          "attraction": {
              "within_zone_time": -0.03094
          },
          "impedance": {
              "time": -0.03094
          },
          "log": {
              "attraction_size": 1
          },
          "attraction_size": {
              "workplaces": 1
          }
      },
      "transit_work": {
          "attraction": {
            "within_zone_inf": -1
          },
          "impedance": {
              "time": -0.01292
          },
          "log": {
              "attraction_size": 1
          },
          "attraction_size": {
              "workplaces": 1
          }
      },
      "bike": {
          "attraction": {
              "within_zone_dist": -0.29461
          },
          "impedance": {
              "dist": -0.29461
          },
          "log": {
              "attraction_size": 1
          },
          "attraction_size": {
              "workplaces": 1
          }
      },
      "walk": {
          "attraction": {
              "within_zone_dist": -0.63196
          },
          "impedance": {
              "dist": -0.63196
          },
          "log": {
              "attraction_size": 1
          },
          "attraction_size": {
              "population": 1
          }
      }
  },
  "mode_choice": {
      "car_work": {
          "constant": 0.24349,
          "generation": {},
          "attraction": {},
          "impedance": {},
          "log": {
              "logsum": 0.68499
          },
          "individual_dummy": {}
      },
      "car_pax": {
          "constant": -3.45706,
          "generation": {},
          "attraction": {},
          "impedance": {},
          "log": {
              "logsum": 0.68499
          },
          "individual_dummy": {}
      },
      "transit_work": {
          "constant": -2.4864,
          "generation": {},
          "attraction": {},
          "impedance": {},
          "log": {
              "logsum": 0.68499
          },
          "individual_dummy": {}
      },
      "bike": {
          "constant": -1.73159,
          "generation": {},
          "attraction": {},
          "impedance": {},
          "log": {
              "logsum": 0.68499
          },
          "individual_dummy": {}
      },
      "walk": {
          "constant": 0,
          "generation": {},
          "attraction": {},
          "impedance": {},
          "log": {
              "logsum": 0.68499
          },
          "individual_dummy": {}
      }
  },
    "demand_share": {
        "car_work": {
            "aht": [
                0.1311,
                0.0031
              ],
              "pt": [
                0.096,
                0.112
              ],
              "iht": [
                0.0056,
                0.1392
              ]
        },
        "car_pax": {
            "aht": [
                0.1311,
                0.0031
              ],
              "pt": [
                0.096,
                0.112
              ],
              "iht": [
                0.0056,
                0.1392
              ]
        },
        "transit_work": {
            "aht": [
                0.1311,
                0.0031
              ],
              "pt": [
                0.096,
                0.112
              ],
              "iht": [
                0.0056,
                0.1392
              ]
        },
        "bike": {
            "aht": [
                0.1311,
                0.0031
              ],
              "pt": [
                0.096,
                0.112
              ],
              "iht": [
                0.0056,
                0.1392
              ]
        },
        "walk": {
            "aht": [
                0.1311,
                0.0031
              ],
              "pt": [
                0.096,
                0.112
              ],
              "iht": [
                0.0056,
                0.1392
              ]
        }
    }
}
